mongoy/__init__.py
mongoy/mongo.py
mongoy-0.1.5.dist-info/LICENSE
mongoy-0.1.5.dist-info/METADATA
mongoy-0.1.5.dist-info/WHEEL
mongoy-0.1.5.dist-info/top_level.txt
mongoy-0.1.5.dist-info/RECORD
