Metadata-Version: 2.1
Name: mongoy
Version: 0.1.5
Summary: wrapper utility for mongodb
Author: pavittarx
Classifier: Programming Language :: Python :: 3
Classifier: License :: OSI Approved :: MIT License
Classifier: Operating System :: OS Independent
Requires-Python: >=3.6
License-File: LICENSE
Requires-Dist: pymongo
Requires-Dist: certifi
